pnorm/__init__.py
pnorm/async_client.py
pnorm/async_cursor.py
pnorm/credentials.py
pnorm/exceptions.py
pnorm/mapping_utilities.py
pnorm/pnorm_types.py
pnorm/py.typed
pnorm/sync_client.py
pnorm/hooks/__init__.py
pnorm/hooks/base.py
pnorm/hooks/opentelemetry.py
pnorm-0.0.2.dist-info/METADATA
pnorm-0.0.2.dist-info/WHEEL
pnorm-0.0.2.dist-info/licenses/LICENSE
pnorm-0.0.2.dist-info/RECORD
