Metadata-Version: 2.4
Name: pnorm
Version: 0.0.2
Summary: Postgres Not an ORM
Project-URL: Repository, https://github.com/alrudolph/pnorm
Author-email: Alex Rudolph <alex@voker.ai>
License-File: LICENSE
Requires-Python: ~=3.11
Requires-Dist: opentelemetry-sdk<2,>=1.29.0
Requires-Dist: psycopg[binary]<4,>=3.2.1
Requires-Dist: pydantic<3,>=2.5.2
Requires-Dist: rcheck<0.0.11,>=0.0.10
